{
  "project_info": {
    "project_number": "1092786719601",
    "project_id": "multiscloud-phone",
    "storage_bucket": "multiscloud-phone.appspot.com"
  },
  "client": [
    {
      "client_info": {
        "mobilesdk_app_id": "1:1092786719601:android:fb042cb53cdc09c82544d0",
        "android_client_info": {
          "package_name": "com.infinitaz.multiscloudphone"
        }
      },
      "oauth_client": [
        {
          "client_id": "1092786719601-hm4msgv15igaksctmn3t9mj9v0i85tp7.apps.googleusercontent.com",
          "client_type": 3
        }
      ],
      "api_key": [
        {
          "current_key": "AIzaSyAKk8veNxq8ji3MTmoZ3_xWJgYH3A5HKoU"
        }
      ],
      "services": {
        "appinvite_service": {
          "other_platform_oauth_client": [
            {
              "client_id": "1092786719601-hm4msgv15igaksctmn3t9mj9v0i85tp7.apps.googleusercontent.com",
              "client_type": 3
            }
          ]
        }
      }
    },
    {
      "client_info": {
        "mobilesdk_app_id": "1:1092786719601:android:a579037cab944b1c2544d0",
        "android_client_info": {
          "package_name": "com.infinitaz.multiscloudphone.debug"
        }
      },
      "oauth_client": [
        {
          "client_id": "1092786719601-hm4msgv15igaksctmn3t9mj9v0i85tp7.apps.googleusercontent.com",
          "client_type": 3
        }
      ],
      "api_key": [
        {
          "current_key": "AIzaSyAKk8veNxq8ji3MTmoZ3_xWJgYH3A5HKoU"
        }
      ],
      "services": {
        "appinvite_service": {
          "other_platform_oauth_client": [
            {
              "client_id": "1092786719601-hm4msgv15igaksctmn3t9mj9v0i85tp7.apps.googleusercontent.com",
              "client_type": 3
            }
          ]
        }
      }
    }
  ],
  "configuration_version": "1"
}